firedantic/__init__.py
firedantic/_async/__init__.py
firedantic/_async/helpers.py
firedantic/_async/indexes.py
firedantic/_async/model.py
firedantic/_async/ttl_policy.py
firedantic/_sync/__init__.py
firedantic/_sync/helpers.py
firedantic/_sync/indexes.py
firedantic/_sync/model.py
firedantic/_sync/ttl_policy.py
firedantic/common.py
firedantic/configurations.py
firedantic/exceptions.py
firedantic/operators.py
firedantic/tests/__init__.py
firedantic/tests/test_utils.py
firedantic/tests/tests_async/__init__.py
firedantic/tests/tests_async/conftest.py
firedantic/tests/tests_async/test_indexes.py
firedantic/tests/tests_async/test_model.py
firedantic/tests/tests_async/test_ttl_policy.py
firedantic/tests/tests_sync/__init__.py
firedantic/tests/tests_sync/conftest.py
firedantic/tests/tests_sync/test_indexes.py
firedantic/tests/tests_sync/test_model.py
firedantic/tests/tests_sync/test_ttl_policy.py
firedantic/utils.py
firedantic-0.11.0.dist-info/LICENSE
firedantic-0.11.0.dist-info/METADATA
firedantic-0.11.0.dist-info/WHEEL
firedantic-0.11.0.dist-info/RECORD
