Metadata-Version: 2.1
Name: firedantic
Version: 0.11.0
Summary: Pydantic base models for Firestore
Home-page: https://github.com/ioxiocom/firedantic
License: BSD-3-Clause
Author: IOXIO Ltd
Requires-Python: >=3.9,<4.0
Classifier: License :: OSI Approved :: BSD License
Classifier: Programming Language :: Python :: 3
Classifier: Programming Language :: Python :: 3.9
Classifier: Programming Language :: Python :: 3.10
Classifier: Programming Language :: Python :: 3.11
Classifier: Programming Language :: Python :: 3.12
Classifier: Programming Language :: Python :: 3.13
Requires-Dist: google-cloud-firestore (>=2.20.0,<3.0.0)
Requires-Dist: grpcio (>=1.70.0,<2.0.0)
Requires-Dist: pydantic (>=2.10.6,<3.0.0)
Project-URL: Repository, https://github.com/ioxiocom/firedantic
